sajupy/__init__.py
sajupy/calendar_data.csv
sajupy/core.py
sajupy-0.2.0.dist-info/licenses/LICENSE
sajupy-0.2.0.dist-info/METADATA
sajupy-0.2.0.dist-info/WHEEL
sajupy-0.2.0.dist-info/top_level.txt
sajupy-0.2.0.dist-info/RECORD
